timy_cli/__init__.py
timy_cli/__main__.py
timy_cli/timy.py
timy_cli-2.0.0.dist-info/LICENSE
timy_cli-2.0.0.dist-info/METADATA
timy_cli-2.0.0.dist-info/WHEEL
timy_cli-2.0.0.dist-info/entry_points.txt
timy_cli-2.0.0.dist-info/top_level.txt
timy_cli-2.0.0.dist-info/RECORD
